pythonlogbook/__init__.py
pythonlogbook/addentry.py
pythonlogbook/combineLogs.py
pythonlogbook-1.2.7.dist-info/LICENSE.md
pythonlogbook-1.2.7.dist-info/METADATA
pythonlogbook-1.2.7.dist-info/WHEEL
pythonlogbook-1.2.7.dist-info/entry_points.txt
pythonlogbook-1.2.7.dist-info/top_level.txt
pythonlogbook-1.2.7.dist-info/RECORD
