Metadata-Version: 2.1
Name: pythonlogbook
Version: 1.2.7
Summary: A simple logbook made with python
Home-page: https://github.com/lukew3/logbook
Author: Luke Weiler
Author-email: lukew25073@gmail.com
License: MIT
Platform: UNKNOWN
Requires-Dist: mdutils
